api/__init__.py
api/serializers.py
api/views.py
remauth/__init__.py
remauth/apps.py
remauth/urls.py
remauth/views.py
remauth/api/__init__.py
remauth/api/serializers.py
remauth/api/views.py
django_remauth-0.1.4.dist-info/LICENSE
django_remauth-0.1.4.dist-info/METADATA
django_remauth-0.1.4.dist-info/WHEEL
django_remauth-0.1.4.dist-info/top_level.txt
django_remauth-0.1.4.dist-info/RECORD
